aoikhotkey/__init__.py
aoikhotkey/__main__.py
aoikhotkey/compat.py
aoikhotkey/const.py
aoikhotkey/event_manager.py
aoikhotkey/event_manager_cygwin.py
aoikhotkey/event_manager_macos.py
aoikhotkey/event_manager_windows.py
aoikhotkey/event_manager_x11.py
aoikhotkey/hotkey_manager.py
aoikhotkey/hotkey_parser.py
aoikhotkey/hotkey_spec_parser.py
aoikhotkey/mediator.py
aoikhotkey/mediator_argpsr.py
aoikhotkey/runtime.py
aoikhotkey/task_manager.py
aoikhotkey/version.py
aoikhotkey/virtualkey.py
aoikhotkey/util/__init__.py
aoikhotkey/util/cmd.py
aoikhotkey/util/efunc.py
aoikhotkey/util/growl.py
aoikhotkey/util/keyboard_winos.py
aoikhotkey/util/mouse_winos.py
aoikhotkey/util/sendkey_winos.py
aoikhotkey/util/tfunc.py
aoikhotkeydep/__init__.py
aoikhotkeydep/aoikimportutil.py
aoikhotkeydep/pyxHook.py
aoikhotkeydep/pyHook_versions/pyHook-py2.7-32bit/pyHook/CHANGELOG.txt
aoikhotkeydep/pyHook_versions/pyHook-py2.7-32bit/pyHook/HookManager.py
aoikhotkeydep/pyHook_versions/pyHook-py2.7-32bit/pyHook/LICENSE.txt
aoikhotkeydep/pyHook_versions/pyHook-py2.7-32bit/pyHook/README.txt
aoikhotkeydep/pyHook_versions/pyHook-py2.7-32bit/pyHook/__init__.py
aoikhotkeydep/pyHook_versions/pyHook-py2.7-32bit/pyHook/_cpyHook.pyd
aoikhotkeydep/pyHook_versions/pyHook-py2.7-32bit/pyHook/aa hook.py
aoikhotkeydep/pyHook_versions/pyHook-py2.7-32bit/pyHook/cpyHook.py
aoikhotkeydep/pyHook_versions/pyHook-py2.7-32bit/pyHook/doc.py
aoikhotkeydep/pyHook_versions/pyHook-py2.7-32bit/pyHook/example.py
aoikhotkeydep/pyHook_versions/pyHook-py2.7-64bit/pyHook/CHANGELOG.txt
aoikhotkeydep/pyHook_versions/pyHook-py2.7-64bit/pyHook/HookManager.py
aoikhotkeydep/pyHook_versions/pyHook-py2.7-64bit/pyHook/LICENSE.txt
aoikhotkeydep/pyHook_versions/pyHook-py2.7-64bit/pyHook/README.txt
aoikhotkeydep/pyHook_versions/pyHook-py2.7-64bit/pyHook/__init__.py
aoikhotkeydep/pyHook_versions/pyHook-py2.7-64bit/pyHook/_cpyHook.pyd
aoikhotkeydep/pyHook_versions/pyHook-py2.7-64bit/pyHook/aa hook.py
AoikHotkey-0.7.0.dist-info/LICENSE.txt
AoikHotkey-0.7.0.dist-info/METADATA
AoikHotkey-0.7.0.dist-info/WHEEL
AoikHotkey-0.7.0.dist-info/entry_points.txt
AoikHotkey-0.7.0.dist-info/top_level.txt
AoikHotkey-0.7.0.dist-info/RECORD
